MANIFEST.in
requirements.txt
setup.cfg
setup.py
powerglove_dns/__init__.py
powerglove_dns/model.py
powerglove_dns/powerglove.py
powerglove_dns.egg-info/PKG-INFO
powerglove_dns.egg-info/SOURCES.txt
powerglove_dns.egg-info/dependency_links.txt
powerglove_dns.egg-info/entry_points.txt
powerglove_dns.egg-info/requires.txt
powerglove_dns.egg-info/top_level.txt
test/__init__.py
test/test_command_line.py
test/test_core.py
test/test_model.py