Metadata-Version: 1.0
Name: powerglove-dns
Version: 2.0.0
Summary: Reserves an appropriate ip in a PowerDNS installation for a given hostname, updating reverse/forward/text records as well
Home-page: https://github.com/appliedsec/Powerglove-DNS
Author: Rob Dennis
Author-email: rdennis+powerglove-dns@gmail.com
License: UNKNOWN
Platform: UNKNOWN
Classifier: License :: OSI Approved :: MIT License
Classifier: Development Status :: 5 - Production/Stable
